unicodemoticon/__init__.py
unicodemoticon/__main__.py
unicodemoticon/unicodemoticon.desktop
unicodemoticon/core/data.py
unicodemoticon/core/faderwidget.py
unicodemoticon/core/scrollgroup.py
unicodemoticon/core/tabbar.py
unicodemoticon/core/tinyslation.py
unicodemoticon/tabs/tab_html.py
unicodemoticon/tabs/tab_recent.py
unicodemoticon/tabs/tab_search.py
unicodemoticon/tabs/tab_symbols.py
unicodemoticon/tabs/tab_tool.py
unicodemoticon-3.0.0.dist-info/DESCRIPTION.rst
unicodemoticon-3.0.0.dist-info/METADATA
unicodemoticon-3.0.0.dist-info/RECORD
unicodemoticon-3.0.0.dist-info/WHEEL
unicodemoticon-3.0.0.dist-info/entry_points.txt
unicodemoticon-3.0.0.dist-info/metadata.json
unicodemoticon-3.0.0.dist-info/top_level.txt
unicodemoticon-3.0.0.dist-info/zip-safe
