Metadata-Version: 2.0
Name: unicodemoticon
Version: 3.0.0
Summary: Emoji App. Like a Color Picker but for Unicode Emoticons. Trayicon with Unicode Emoticons using Python3 Qt5.
Home-page: https://github.com/juancarlospaco/unicodemoticon#unicodemoticon
Author: Juan Carlos 
Author-email: juancarlospaco@gmail.com
License: GPLv3+ LGPLv3+ 
Keywords: Unicode,Emoticon,Smilies,Qt,HTML5,HTML Entity
Platform: UNKNOWN
Classifier: Development Status :: 5 - Production/Stable
Classifier: Intended Audience :: Developers
Classifier: Intended Audience :: End Users/Desktop
Classifier: Intended Audience :: System Administrators
Classifier: Intended Audience :: Information Technology
Classifier: Intended Audience :: Other Audience
Classifier: Natural Language :: English
Classifier: License :: OSI Approved :: GNU General Public License (GPL)
Classifier: License :: OSI Approved :: GNU Library or Lesser General Public License (LGPL)
Classifier: License :: OSI Approved :: GNU Lesser General Public License v3 or later (LGPLv3+)
Classifier: License :: OSI Approved :: GNU General Public License v3 or later (GPLv3+)
Classifier: Operating System :: POSIX :: Linux
Classifier: Programming Language :: Python
Classifier: Programming Language :: Python :: 3
Classifier: Programming Language :: Python :: 3.5
Classifier: Programming Language :: Python :: Implementation :: CPython
Classifier: Programming Language :: Python :: Implementation :: PyPy
Classifier: Topic :: Software Development
Requires: anglerfish
Requires-Dist: anglerfish
